snap_to_bucket/__init__.py
snap_to_bucket/run.py
snap_to_bucket/handlers/__init__.py
snap_to_bucket/handlers/ec_2_handler.py
snap_to_bucket/handlers/fs_handler.py
snap_to_bucket/handlers/s3_handler.py
snap_to_bucket/runner/__init__.py
snap_to_bucket/runner/snap_handler.py
snap_to_bucket-1.0.4.dist-info/LICENSE
snap_to_bucket-1.0.4.dist-info/METADATA
snap_to_bucket-1.0.4.dist-info/WHEEL
snap_to_bucket-1.0.4.dist-info/entry_points.txt
snap_to_bucket-1.0.4.dist-info/top_level.txt
snap_to_bucket-1.0.4.dist-info/RECORD
