Metadata-Version: 2.1
Name: snap-to-bucket
Version: 1.0.4
Summary: Move AWS EBS Snapshots to S3 Buckets
Home-page: https://github.com/siemens/snap-to-bucket/
Author: Gaurav Mishra
Author-email: mishra.gaurav@siemens.com
License: MIT
Keywords: aws,snapshot,bucket,ebs,s3
Classifier: Development Status :: 3 - Alpha
Classifier: Environment :: Console
Classifier: Intended Audience :: System Administrators
Classifier: License :: OSI Approved :: MIT License
Classifier: License :: CC0 1.0 Universal (CC0 1.0) Public Domain Dedication
Classifier: Natural Language :: English
Classifier: Operating System :: OS Independent
Classifier: Programming Language :: Python :: 3 :: Only
Classifier: Topic :: Utilities
Classifier: Topic :: System :: Recovery Tools
Requires-Python: >=3.5
License-File: LICENSE
Requires-Dist: boto3
Requires-Dist: psutil
Requires-Dist: Click
